<?xml version="1.0"?>
<gconf>
	<entry name="active" mtime="1284131122" type="schema" stype="list" owner="hildon-desktop" list_type="int">
		<local_schema locale="C" short_desc="List of the active (enabled) Home views">
			<default type="list" ltype="int">
				<li type="int" value="1"/>
				<li type="int" value="2"/>
				<li type="int" value="3"/>
				<li type="int" value="4"/>
			</default>
		</local_schema>
	</entry>
	<entry name="current" mtime="1284131122" type="schema" stype="int" owner="hildon-desktop">
		<local_schema locale="C" short_desc="The currently shown Home view">
			<default type="int" value="1"/>
		</local_schema>
	</entry>
</gconf>
